fds/__init__.py
fds/sdk/__init__.py
fds/sdk/AxiomaEquityOptimizer/__init__.py
fds/sdk/AxiomaEquityOptimizer/api_client.py
fds/sdk/AxiomaEquityOptimizer/configuration.py
fds/sdk/AxiomaEquityOptimizer/exceptions.py
fds/sdk/AxiomaEquityOptimizer/model_utils.py
fds/sdk/AxiomaEquityOptimizer/rest.py
fds/sdk/AxiomaEquityOptimizer/api/__init__.py
fds/sdk/AxiomaEquityOptimizer/api/accounts_api.py
fds/sdk/AxiomaEquityOptimizer/api/axp_optimizer_api.py
fds/sdk/AxiomaEquityOptimizer/api/currencies_api.py
fds/sdk/AxiomaEquityOptimizer/api/strategy_documents_api.py
fds/sdk/AxiomaEquityOptimizer/apis/__init__.py
fds/sdk/AxiomaEquityOptimizer/model/__init__.py
fds/sdk/AxiomaEquityOptimizer/model/account_directories.py
fds/sdk/AxiomaEquityOptimizer/model/account_directories_root.py
fds/sdk/AxiomaEquityOptimizer/model/axioma_equity_optimization_parameters.py
fds/sdk/AxiomaEquityOptimizer/model/axioma_equity_optimization_parameters_root.py
fds/sdk/AxiomaEquityOptimizer/model/calculation_info.py
fds/sdk/AxiomaEquityOptimizer/model/calculation_info_root.py
fds/sdk/AxiomaEquityOptimizer/model/client_error_response.py
fds/sdk/AxiomaEquityOptimizer/model/currency.py
fds/sdk/AxiomaEquityOptimizer/model/currency_root.py
fds/sdk/AxiomaEquityOptimizer/model/document_directories.py
fds/sdk/AxiomaEquityOptimizer/model/document_directories_root.py
fds/sdk/AxiomaEquityOptimizer/model/error.py
fds/sdk/AxiomaEquityOptimizer/model/error_source.py
fds/sdk/AxiomaEquityOptimizer/model/object_root.py
fds/sdk/AxiomaEquityOptimizer/model/optimal_portfolio.py
fds/sdk/AxiomaEquityOptimizer/model/optimization.py
fds/sdk/AxiomaEquityOptimizer/model/optimizer_account.py
fds/sdk/AxiomaEquityOptimizer/model/optimizer_account_overrides.py
fds/sdk/AxiomaEquityOptimizer/model/optimizer_optimal_holdings.py
fds/sdk/AxiomaEquityOptimizer/model/optimizer_output_types.py
fds/sdk/AxiomaEquityOptimizer/model/optimizer_strategy.py
fds/sdk/AxiomaEquityOptimizer/model/optimizer_strategy_overrides.py
fds.sdk.AxiomaEquityOptimizer-0.21.14.dist-info/LICENSE
fds.sdk.AxiomaEquityOptimizer-0.21.14.dist-info/METADATA
fds.sdk.AxiomaEquityOptimizer-0.21.14.dist-info/WHEEL
fds.sdk.AxiomaEquityOptimizer-0.21.14.dist-info/top_level.txt
fds.sdk.AxiomaEquityOptimizer-0.21.14.dist-info/RECORD
